LICENSE
MANIFEST.in
README.md
setup.cfg
setup.py
versioneer.py
./.gitattributes
./CODE_OF_CONDUCT.md
./CONTRIBUTING.md
./LICENSE
./MANIFEST.in
./README.md
./setup.cfg
./setup.py
./versioneer.py
./ruleskit/__init__.py
./ruleskit/_version.py
./ruleskit/activation.py
./ruleskit/condition.py
./ruleskit/rule.py
./ruleskit/ruleset.py
./ruleskit/thresholds.py
./ruleskit.egg-info/PKG-INFO
./ruleskit.egg-info/SOURCES.txt
./ruleskit.egg-info/dependency_links.txt
./ruleskit.egg-info/requires.txt
./ruleskit.egg-info/top_level.txt
./ruleskit/utils/__init__.py
./ruleskit/utils/rfunctions.py
./ruleskit/utils/rule_utils.py
./tests/__init__.py
./tests/unit/__init__.py
./tests/unit/conftest.py
./tests/unit/test_activation.py
./tests/unit/test_condition.py
./tests/unit/test_rfunctions.py
./tests/unit/test_rule.py
./tests/unit/test_rule_utils.py
./tests/unit/test_ruleset.py
./tests/unit/test_thresholds.py
./tests/unit/data/a1.txt
./tests/unit/data/a1_activation_init_bitarray.csv
./tests/unit/data/a1_activation_init_bitarray_after_calls.csv
./tests/unit/data/a1_activation_init_compressed_array.csv
./tests/unit/data/a1_activation_init_compressed_array_after_calls.csv
./tests/unit/data/a1_activation_init_compressed_str.csv
./tests/unit/data/a1_activation_init_compressed_str_after_calls.csv
./tests/unit/data/a1_activation_init_file.csv
./tests/unit/data/a1_activation_init_file_after_calls.csv
./tests/unit/data/a1_activation_init_integer.csv
./tests/unit/data/a1_activation_init_integer_after_calls.csv
./tests/unit/data/a1_activation_init_raw.csv
./tests/unit/data/a1_activation_init_raw_after_calls.csv
./tests/unit/data/a2.txt
./tests/unit/data/a2_activation_init_bitarray.csv
./tests/unit/data/a2_activation_init_bitarray_after_calls.csv
./tests/unit/data/a2_activation_init_compressed_array.csv
./tests/unit/data/a2_activation_init_compressed_array_after_calls.csv
./tests/unit/data/a2_activation_init_compressed_str.csv
./tests/unit/data/a2_activation_init_compressed_str_after_calls.csv
./tests/unit/data/a2_activation_init_file.csv
./tests/unit/data/a2_activation_init_file_after_calls.csv
./tests/unit/data/a2_activation_init_integer.csv
ruleskit.egg-info/PKG-INFO
ruleskit.egg-info/SOURCES.txt
ruleskit.egg-info/dependency_links.txt
ruleskit.egg-info/requires.txt
ruleskit.egg-info/top_level.txt
