Metadata-Version: 2.1
Name: ruleskit
Version: 1.0.118
Summary: Generic rule package for rule-based algorithms
Home-page: https://github.com/Advestis/ruleskit
Author: P.Cotte & V.Margot
Author-email: pythondev@advestis.com
License: GPLv3
Project-URL: Bug Tracker, https://github.com/Advestis/ruleskit/issues
Project-URL: Documentation, https://advestis.github.io/ruleskit
Project-URL: Source Code, https://github.com/Advestis/ruleskit/
Platform: UNKNOWN
Classifier: Development Status :: 5 - Production/Stable
Classifier: License :: OSI Approved :: GNU General Public License v3 (GPLv3)
Classifier: Operating System :: Unix
Classifier: Programming Language :: Python :: 3.7
Classifier: Programming Language :: Python :: 3.8
Classifier: Programming Language :: Python :: 3.9
Requires-Python: >=3.7
License-File: LICENSE
